pytask/__init__.py
pytask/__main__.py
pytask/flags/__init__.py
pytask/flags/flags.py
pytask/job/__init__.py
pytask/job/job.py
pytask/job/types.py
pytask/task_queue/__init__.py
pytask/task_queue/constants.py
pytask/task_queue/task_queue.py
pytask/task_queue/types.py
pytask/worker/__init__.py
pytask/worker/async_worker.py
pytask/worker/base_worker.py
pytask/worker/concurrent_worker.py
pytask/worker/worker.py
pytask_queue-1.0.3.dist-info/LICENSE
pytask_queue-1.0.3.dist-info/METADATA
pytask_queue-1.0.3.dist-info/WHEEL
pytask_queue-1.0.3.dist-info/top_level.txt
pytask_queue-1.0.3.dist-info/RECORD
