Metadata-Version: 2.1
Name: pytask-queue
Version: 1.0.3
Summary: A simple queue for Python tasks
Author-email: Jayden Pyles <jpylesbusiness@gmail.com>
License: MIT
Project-URL: repository, https://github.com/jaypyles/pytask
Requires-Python: >=3.10
License-File: LICENSE
Requires-Dist: typing-extensions>=4.12.2
